docmesh/__init__.py
docmesh/db/__init__.py
docmesh/db/auth.py
docmesh/db/neo.py
docmesh/utils/__init__.py
docmesh/utils/graph_utils.py
docmesh/utils/semantic_scholar.py
docmesh-0.0.5.dist-info/WHEEL
docmesh-0.0.5.dist-info/METADATA
docmesh-0.0.5.dist-info/RECORD
