Metadata-Version: 2.1
Name: docmesh
Version: 0.0.5
Summary: Core components for docmesh.
Author-email: Zhengkai Yang <kyle.yang1995@gmail.com>
Requires-Python: >=3.8
Classifier: Programming Language :: Python :: 3.8
Classifier: Programming Language :: Python :: 3.9
Classifier: Programming Language :: Python :: 3.10
Classifier: Operating System :: OS Independent
Requires-Dist: retry>=0.9.2
Requires-Dist: numpy>=1.26.4
Requires-Dist: scipy>=1.13.0
Requires-Dist: pandas>=2.2.2
Requires-Dist: networkx>=3.2
Requires-Dist: matplotlib>=3.8.4
Requires-Dist: neomodel>=5.3.0
Requires-Dist: pymysql>=0.9.3
Requires-Dist: sqlalchemy>=2
